LICENSE
MANIFEST.in
README.md
requirements.txt
setup.cfg
setup.py
flink_sql_runner/__init__.py
flink_sql_runner/cmd_utils.py
flink_sql_runner/deploy.py
flink_sql_runner/deploy_job.py
flink_sql_runner/flink_clients.py
flink_sql_runner/jinja.py
flink_sql_runner/job_configuration.py
flink_sql_runner/manifest.py
flink_sql_runner/s3.py
flink_sql_runner.egg-info/PKG-INFO
flink_sql_runner.egg-info/SOURCES.txt
flink_sql_runner.egg-info/dependency_links.txt
flink_sql_runner.egg-info/requires.txt
flink_sql_runner.egg-info/top_level.txt
flink_sql_runner/runner/run-flink-code.py.jinja2
flink_sql_runner/runner/run-flink-sql.py