Metadata-Version: 2.1
Name: flink-sql-runner
Version: 0.2.0
Summary: Framework for scheduling streaming SQL queries on Apache Hadoop YARN and on a standalone Flink cluster.
Home-page: UNKNOWN
License: UNKNOWN
Platform: UNKNOWN
Classifier: Programming Language :: Python :: 3.7
Classifier: Operating System :: OS Independent
Requires-Python: >=3.7
